codelogic_mcp_server/__init__.py
codelogic_mcp_server/handlers.py
codelogic_mcp_server/server.py
codelogic_mcp_server/utils.py
codelogic_mcp_server-1.0.11.dist-info/METADATA
codelogic_mcp_server-1.0.11.dist-info/WHEEL
codelogic_mcp_server-1.0.11.dist-info/entry_points.txt
codelogic_mcp_server-1.0.11.dist-info/licenses/LICENSE
codelogic_mcp_server-1.0.11.dist-info/RECORD
