Metadata-Version: 2.4
Name: codelogic-mcp-server
Version: 1.0.11
Summary: Integrates CodeLogic's powerful codebase knowledge graphs with a Model Context Protocol (MCP) server
Project-URL: Homepage, https://github.com/CodeLogicIncEngineering/codelogic-mcp-server
Project-URL: Bug Tracker, https://github.com/CodeLogicIncEngineering/codelogic-mcp-server/issues
Project-URL: Documentation, https://github.com/CodeLogicIncEngineering/codelogic-mcp-server#readme
Author-email: garrmark <mgarrison@codelogic.com>
License-Expression: MPL-2.0
License-File: LICENSE
Keywords: code-analysis,codelogic,knowledge-graph,mcp,static-analysis
Classifier: Development Status :: 4 - Beta
Classifier: Environment :: Console
Classifier: Intended Audience :: Developers
Classifier: Operating System :: OS Independent
Classifier: Programming Language :: Python :: 3
Classifier: Programming Language :: Python :: 3.13
Classifier: Topic :: Software Development
Classifier: Topic :: Software Development :: Code Generators
Classifier: Topic :: Software Development :: Libraries :: Python Modules
Requires-Python: >=3.13
Requires-Dist: debugpy>=1.8.12
Requires-Dist: httpx>=0.28.1
Requires-Dist: mcp[cli]>=1.3.0
Requires-Dist: pip-licenses>=5.0.0
Requires-Dist: python-dotenv>=1.0.1
Requires-Dist: tenacity>=9.0.0
Requires-Dist: toml>=0.10.2
